cryptg/__init__.py
telethon_cryptg-0.0.4.dist-info/LICENSE
telethon_cryptg-0.0.4.dist-info/METADATA
telethon_cryptg-0.0.4.dist-info/WHEEL
telethon_cryptg-0.0.4.dist-info/top_level.txt
telethon_cryptg-0.0.4.dist-info/RECORD
